[
    {
        "icons": "<MdGroups />",
        "title": "Enjoy Learning From Anywhere ",
        "content": "We are delighted to give you options to enjoy learning from anywhere in the world."
    },
    {
        "icons": "<MdGroups />",
        "title": "Learn From Industry Experts",
        "content": "Experienced teachers can assist in learning faster with their best approaches!"
    },
    {
        "icons": "<MdGroups />",
        "title": "Earn Juicy Commission",
        "content": "Get familiar with digital and financial literacy skills in your journey of becoming stable"
    },
    {
        "icons": "<MdGroups />",
        "title": "Learn the Latest Top Skills",
        "content": "Learning top skills can give you the extra incentive to push your career further."
    }
]